{
  "ExtendedData": {
    "inputs": [
      "http://localhost:63906/Service1.svc"
    ],
    "collectionTypes": [
      "System.Collections.Generic.Dictionary`2",
      "System.Collections.Generic.List`1"
    ],
    "messageContract": true,
    "namespaceMappings": [
      "*, MobilneHotelServiceReference"
    ],
    "references": [
      "System.Numerics.Vectors, {System.Numerics.Vectors, 4.5.0}",
      "System.ServiceModel, {System.ServiceModel.Primitives, 4.4.4}",
      "System.ServiceModel.Duplex, {System.ServiceModel.Duplex, 4.4.4}",
      "System.ServiceModel.Http, {System.ServiceModel.Http, 4.4.4}",
      "System.ServiceModel.NetTcp, {System.ServiceModel.NetTcp, 4.4.4}",
      "System.ServiceModel.Primitives, {System.ServiceModel.Primitives, 4.4.4}",
      "System.ServiceModel.Security, {System.ServiceModel.Security, 4.4.4}",
      "Xamarin.Essentials, {Xamarin.Essentials, 1.6.1}",
      "Xamarin.Forms.Core, {Xamarin.Forms, 5.0.0.2012}",
      "Xamarin.Forms.Platform, {Xamarin.Forms, 5.0.0.2012}",
      "Xamarin.Forms.Xaml, {Xamarin.Forms, 5.0.0.2012}"
    ],
    "sync": true,
    "targetFramework": "netstandard2.0",
    "typeReuseMode": "All"
  }
}